sigit/__init__.py
sigit/custom_widgets.kv
sigit/custom_widgets.py
sigit/main.kv
sigit/main.py
sigit/assets/fonts/DejaVuSansMono.ttf
sigit-0.0.58.dist-info/METADATA
sigit-0.0.58.dist-info/WHEEL
sigit-0.0.58.dist-info/entry_points.txt
sigit-0.0.58.dist-info/RECORD
