Metadata-Version: 2.3
Name: sigit
Version: 0.0.58
Summary: A Git GUI built with Python and Kivy
Author-email: Your Name <your.email@example.com>
License: MIT
Keywords: git,gui,kivy,python
Classifier: Operating System :: OS Independent
Classifier: Programming Language :: Python :: 3
Requires-Python: >=3.7
Requires-Dist: kivy>=2.0.0
Requires-Dist: pygments>=2.7.0
